tracta_ml/dispout.py
tracta_ml/evolve.cp35-win_amd64.pyd
tracta_ml/genetic_operators.cp35-win_amd64.pyd
tracta_ml/model_optimizer.cp35-win_amd64.pyd
tracta_ml/pool_maintenance.cp35-win_amd64.pyd
tracta_ml-1.2.5.dist-info/DESCRIPTION.rst
tracta_ml-1.2.5.dist-info/METADATA
tracta_ml-1.2.5.dist-info/RECORD
tracta_ml-1.2.5.dist-info/WHEEL
tracta_ml-1.2.5.dist-info/metadata.json
tracta_ml-1.2.5.dist-info/top_level.txt
