Metadata-Version: 2.0
Name: tracta-ml
Version: 1.2.5
Summary: Combined hyper-parameter optimization and feature selection      for machine learning models using micro genetic algorithms
Home-page: https://github.com/SankethNagarajan/tracta_ml
Author: Sanketh Nagarajan
Author-email: sanketh.objml@gmail.com
License: BSD 3-Clause "New" or "Revised" License
Platform: UNKNOWN
Classifier: Development Status :: 3 - Alpha
Classifier: License :: OSI Approved :: BSD License
Classifier: Programming Language :: Python :: 3.5
Requires-Dist: datetime
Requires-Dist: matplotlib
Requires-Dist: numpy
Requires-Dist: pandas
Requires-Dist: sklearn
